iot_protocol_rule_py3/__init__.py
iot_protocol_rule_py3/protocol_rule_adcp.py
iot_protocol_rule_py3/protocol_rule_all_canal.py
iot_protocol_rule_py3/protocol_rule_atmk_gate.py
iot_protocol_rule_py3/protocol_rule_ctwing_huizhong.py
iot_protocol_rule_py3/protocol_rule_ctwing_maituo.py
iot_protocol_rule_py3/protocol_rule_ctwing_ylsk.py
iot_protocol_rule_py3/protocol_rule_ecois.py
iot_protocol_rule_py3/protocol_rule_electromagnetic_water_meter.py
iot_protocol_rule_py3/protocol_rule_fd.py
iot_protocol_rule_py3/protocol_rule_flow_dlty.py
iot_protocol_rule_py3/protocol_rule_grm_cmqzm.py
iot_protocol_rule_py3/protocol_rule_grm_flow_meter.py
iot_protocol_rule_py3/protocol_rule_grm_ltsp.py
iot_protocol_rule_py3/protocol_rule_grm_pump.py
iot_protocol_rule_py3/protocol_rule_grm_sjt.py
iot_protocol_rule_py3/protocol_rule_grm_tysbz.py
iot_protocol_rule_py3/protocol_rule_grm_wlp.py
iot_protocol_rule_py3/protocol_rule_http_kede_nb.py
iot_protocol_rule_py3/protocol_rule_http_longi_nb.py
iot_protocol_rule_py3/protocol_rule_http_mq_flow_meter.py
iot_protocol_rule_py3/protocol_rule_hydrology_monitor.py
iot_protocol_rule_py3/protocol_rule_hydrology_standard.py
iot_protocol_rule_py3/protocol_rule_hyf_controller.py
iot_protocol_rule_py3/protocol_rule_insect_situation.py
iot_protocol_rule_py3/protocol_rule_jdsk_monitor.py
iot_protocol_rule_py3/protocol_rule_jxct.py
iot_protocol_rule_py3/protocol_rule_kd_gate.py
iot_protocol_rule_py3/protocol_rule_lora.py
iot_protocol_rule_py3/protocol_rule_lora_water_meter.py
iot_protocol_rule_py3/protocol_rule_lot.py
iot_protocol_rule_py3/protocol_rule_ltq_wqm.py
iot_protocol_rule_py3/protocol_rule_maituo.py
iot_protocol_rule_py3/protocol_rule_mingnew.py
iot_protocol_rule_py3/protocol_rule_new_kd.py
iot_protocol_rule_py3/protocol_rule_new_sky.py
iot_protocol_rule_py3/protocol_rule_ngn_gda_16.py
iot_protocol_rule_py3/protocol_rule_photovoltaic_controller.py
iot_protocol_rule_py3/protocol_rule_plc_cxt_gate.py
iot_protocol_rule_py3-2.2.0.dist-info/LICENSE
iot_protocol_rule_py3-2.2.0.dist-info/METADATA
iot_protocol_rule_py3-2.2.0.dist-info/WHEEL
iot_protocol_rule_py3-2.2.0.dist-info/top_level.txt
iot_protocol_rule_py3-2.2.0.dist-info/RECORD
