Metadata-Version: 2.1
Name: iot_protocol_rule_py3
Version: 2.2.0
Summary: iot_protocol_rule_py3
Home-page: https://gitee.com/ikxyang/iot_protocol_rule_py3
Author: ikxyang
Author-email: sosdawn@163.com
License: UNKNOWN
Project-URL: Bug Tracker, https://gitee.com/ikxyang/iot_protocol_rule_py3/issues
Platform: UNKNOWN
Classifier: Programming Language :: Python :: 3
Classifier: License :: OSI Approved :: MIT License
Classifier: Operating System :: OS Independent
Requires-Python: >=3.5
License-File: LICENSE
